{
  "$schema": "https://schema.management.azure.com/schemas/2015-01-01/deploymentTemplate.json#",
  "contentVersion": "1.0.0.0",
  "parameters": {
    "backupInfo": {
      "type": "object"
    }
  },
  "variables": {},
  "resources": [
    {
      "apiVersion": "2016-06-01",
      "name": "concat([parameters('backupInfo').rcVaultName,'/',parameters('backupInfo').backupPolicy])",
      "type": "Microsoft.RecoveryServices/vaults/backupPolicies",
      "dependsOn": [],
      "location": "[resourceGroup().location]",
      "properties": {
        "backupManagementType": "AzureIaasVM",
        "schedulePolicy": {
          "scheduleRunFrequency": "Daily",
          //"scheduleRunDays": "[parameters('backupInfo').backupDaysOfTheWeek]",
          "scheduleRunTimes": "[parameters('backupInfo').backupScheduleRunTimes]",
          "schedulePolicyType": "SimpleSchedulePolicy"
        },
        "retentionPolicy": {
          "dailySchedule": {
            "retentionTimes": [ "[parameters('backupInfo').backupScheduleRunTimes]" ],
            "retentionDuration": {
              "count": "[parameters('backupInfo').backupDailyRetentionDurationCount]",
              "durationType": "Days"
            }
          },
          "weeklySchedule": {
            "daysOfTheWeek": "[parameters('backupInfo').backupDaysOfTheWeek]",
            "retentionTimes": "[parameters('backupInfo').backupScheduleRunTimes]",
            "retentionDuration": {
              "count": "[parameters('backupInfo').backupWeeklyRetentionDurationCount]",
              "durationType": "Weeks"
            }
          },
          "monthlySchedule": {
            "retentionScheduleFormatType": "Weekly",
            /*"retentionScheduleDaily": {
                "daysOfTheMonth": [
                  {
                    "date": 1,
                    "isLast": false
                  }
                ]
              },*/
            "retentionScheduleWeekly": {
              "daysOfTheWeek": "[parameters('backupInfo').backupDaysOfTheWeek]",
              "weeksOfTheMonth": "[parameters('backupInfo').backupWeeksOfTheMonth]"
            },
            "retentionTimes": "[parameters('backupInfo').backupScheduleRunTimes]",
            "retentionDuration": {
              "count": "[parameters('backupInfo').backupMonthlyRetentionDurationCount]",
              "durationType": "Months"
            }
          },
          "yearlySchedule": {
            "retentionScheduleFormatType": "Weekly",
            "monthsOfYear": "[parameters('backupInfo').backupMonthsOfYear]",
            /*"retentionScheduleDaily": {
                "daysOfTheMonth": [
                  {
                    "date": 1,
                    "isLast": false
                  }
                ]
              },*/
            "retentionScheduleWeekly": {
              "daysOfTheWeek": "[parameters('backupInfo').backupDaysOfTheWeek]",
              "weeksOfTheMonth": "[parameters('backupInfo').backupWeeksOfTheMonth]"
            },
            "retentionTimes": "[parameters('backupInfo').backupScheduleRunTimes]",
            "retentionDuration": {
              "count": "[parameters('backupInfo').backupYearlyRetentionDurationCount]",
              "durationType": "Years"
            }
          },
          "retentionPolicyType": "LongTermRetentionPolicy"
        }
      }
    }
  ]
}