{
  "$schema": "https://schema.management.azure.com/schemas/2015-01-01/deploymentTemplate.json#",
  "contentVersion": "1.0.0.0",
  "parameters": {
    "location": {
      "type": "string"
    },
    "virtualNetworkName": {
      "type": "string"
    },
    "virtualNetworkAddressRange": {
      "type": "string"
    },
    "subnetURL": {
      "type": "string"
    }
  },
  "resources": [
    {
      "name": "[parameters('virtualNetworkName')]",
      "type": "Microsoft.Network/virtualNetworks",
      "dependsOn": [],
      "location": "[parameters('location')]",
      "apiVersion": "2015-06-15",
      "tags": {
        "Project": "BluePrint"
      },
      "properties": {
        "addressSpace": {
          "addressPrefixes": [
            "[parameters('virtualNetworkAddressRange')]"
          ]
        },
        "subnets": "[reference('Subnets').outputs.subnets.value]"
      }
    },
    {
      "name": "Subnets",
      "type": "Microsoft.Resources/deployments",
      "apiVersion": "2015-01-01",
      "dependsOn": [],
      "properties": {
        "mode": "Incremental",
        "templateLink": {
          "uri": "[parameters('subnetURL')]",
          "contentVersion": "1.0.0.0"
        },
        "parameters": {}
      }
    }
  ],
  "outputs": {}
}
